qordoba/__init__.py
qordoba/classifier.py
qordoba/cli.py
qordoba/languages.py
qordoba/log.py
qordoba/project.py
qordoba/settings.py
qordoba/sources.py
qordoba/utils.py
qordoba/commands/__init__.py
qordoba/commands/addkey.py
qordoba/commands/delete.py
qordoba/commands/init.py
qordoba/commands/ls.py
qordoba/commands/pull.py
qordoba/commands/push.py
qordoba/commands/status.py
qordoba/commands/utils.py
qordoba-1.7.0.dist-info/DESCRIPTION.rst
qordoba-1.7.0.dist-info/METADATA
qordoba-1.7.0.dist-info/RECORD
qordoba-1.7.0.dist-info/WHEEL
qordoba-1.7.0.dist-info/entry_points.txt
qordoba-1.7.0.dist-info/metadata.json
qordoba-1.7.0.dist-info/top_level.txt
