Metadata-Version: 2.0
Name: qordoba
Version: 1.7.0
Summary: Qordoba command line tool
Home-page: https://www.qordoba.com
Author: Qordoba
Author-email: hello@qordoba.com
License: UNKNOWN
Platform: UNKNOWN
Classifier: Programming Language :: Python
Classifier: Programming Language :: Python :: 2.7
Classifier: Programming Language :: Python :: 3.4
Classifier: Programming Language :: Python :: 3.5
Requires-Dist: tabulate
Requires-Dist: PyYAML (==3.12)
Requires-Dist: requests
Requires-Dist: terminaltables (==3.1.0)
Requires-Dist: furl (==0.5.6)
